square/__init__.py
square/__main__.py
Div_square-1.0.0.dist-info/LICENSE
Div_square-1.0.0.dist-info/METADATA
Div_square-1.0.0.dist-info/WHEEL
Div_square-1.0.0.dist-info/entry_points.txt
Div_square-1.0.0.dist-info/top_level.txt
Div_square-1.0.0.dist-info/RECORD
