Metadata-Version: 2.1
Name: Div-square
Version: 1.0.0
Summary: It squares the number
Home-page: https://github.com/DivyaGoel/Div-square
Author: Divya Goel
Author-email: divyaji.goel@gmail.com.com
License: MIT
Platform: UNKNOWN
Classifier: License :: OSI Approved :: MIT License
Classifier: Programming Language :: Python :: 3.6
Classifier: Programming Language :: Python :: 3.7
Classifier: Programming Language :: Python :: 3.8
